puppygraph/__init__.py
puppygraph/client/__init__.py
puppygraph/client/client.py
puppygraph/common/__init__.py
puppygraph/common/conversion_utils.py
puppygraph/common/dataclass_utils.py
puppygraph/common/test_conversion_utils.py
puppygraph/data/__init__.py
puppygraph/data/host/__init__.py
puppygraph/data/host/host_config.py
puppygraph/data/mapping/__init__.py
puppygraph/data/mapping/catalog_config.py
puppygraph/data/mapping/database_params.py
puppygraph/data/mapping/datalake_params.py
puppygraph/data/mapping/graph_element_cache_config.py
puppygraph/data/mapping/graph_mapping_config.py
puppygraph/data/schema/__init__.py
puppygraph/data/schema/graph_schema.py
puppygraph/rag/__init__.py
puppygraph/rag/graph_agent.py
puppygraph-0.1.5.dist-info/METADATA
puppygraph-0.1.5.dist-info/WHEEL
puppygraph-0.1.5.dist-info/RECORD
