Metadata-Version: 2.1
Name: puppygraph
Version: 0.1.5
Summary: The project contains the PuppyGraph client and PuppyGraph's Agentic Graph RAG libraries for Python. PuppyGraph client enables dynamic graph querying across multiple data sources with zero ETL, flexible schema management, and support for Cypher and Gremlin queries. PuppyGraph agentic graph RAG library makes graph-aware AI Agents.
License: Apache-2.0
Author: PuppyGraph
Author-email: contact@puppygraph.com
Requires-Python: >=3.8.1,<3.12
Classifier: License :: OSI Approved :: Apache Software License
Classifier: Programming Language :: Python :: 3
Classifier: Programming Language :: Python :: 3.9
Classifier: Programming Language :: Python :: 3.10
Classifier: Programming Language :: Python :: 3.11
Requires-Dist: async-timeout (>=4.0.3,<5.0.0)
Requires-Dist: dacite (>=1.7.0,<2.0.0)
Requires-Dist: gremlinpython (>=3.7.2,<4.0.0)
Requires-Dist: jinja2 (>=3.1.4,<4.0.0)
Requires-Dist: langchain-core (>=0.2.33,<0.3.0)
Requires-Dist: neo4j (>=5.7.0,<6.0.0)
Requires-Dist: requests (>=2.28,<3.0)
